constants_importer/__init__.py
constants_importer/import_constants.py
constants_importer_3-9.0.0.dist-info/METADATA
constants_importer_3-9.0.0.dist-info/WHEEL
constants_importer_3-9.0.0.dist-info/top_level.txt
constants_importer_3-9.0.0.dist-info/RECORD
