Metadata-Version: 2.1
Name: constants-importer-3
Version: 9.0.0
Summary: A package for initialising the path to the Constants.py file in a root repo, and then importing said constants into the current directory
Author-email: J J <jai.jalah@krakenflex.com>
Requires-Python: >=3.9
